DEMUX_1_4/DEMUX_1_4.vhd
LIBRARY IEEE;
USE IEEE.std_logic_1164.all;

Entity DEMUX_1_4 is
    port(
        X0 : in std_logic;
        S  : in std_logic_vector(1 downto 0);
        Y0 : out std_logic;
        Y1 : out std_logic;
        Y2 : out std_logic;
        Y3 : out std_logic);
End DEMUX_1_4;

Architecture Simple of DEMUX_1_4 is
    begin
        Y0 <= X0 AND NOT S(1) AND NOT S(0);
        Y1 <= X0 AND NOT S(1) AND S(0);
        Y2 <= X0 AND S(1) AND NOT S(0);
        Y3 <= X0 AND  S(1) AND S(0);
End Simple;

DEMUX_1_4/TB_DEMUX_1_4.vhd
LIBRARY IEEE;
USE IEEE.std_logic_1164.all;

Entity TB_DEMUX_1_4 is

END TB_DEMUX_1_4;

Architecture Simulation of TB_DEMUX_1_4 is
    Component DEMUX_1_4 is 
        port(
            X0 : in std_logic;
            S  : in std_logic_vector(1 downto 0);
            Y0 : out std_logic;
            Y1 : out std_logic;
            Y2 : out std_logic;
            Y3 : out std_logic);
        end Component;
    signal X0, Y0, Y1, Y2, Y3 : std_logic;
    signal S : std_logic_vector(1 downto 0);
    begin
        SIMBLK00 : DEMUX_1_4 PORT MAP (X0,S,Y0,Y1,Y2,Y3);
        process
        begin
            --
            X0 <= '0';
            S  <= "00";
            wait for 20 ns;
            --
            X0 <= '1';
            S  <= "00";
            wait for 20 ns;
            --
            X0 <= '1';
            S  <= "01";
            wait for 20 ns;
            --
            X0 <= '0';
            S  <= "01";
            wait for 20 ns;
            --
            X0 <= '0';
            S  <= "10";
            wait for 20 ns;
            --
            X0 <= '1';
            S  <= "10";
            wait for 20 ns;
            --
            X0 <= '1';
            S  <= "11";
            wait for 20 ns;
            X0 <= '0';
            S  <= "11";
            wait;

    end process;
end Simulation;

DEMUX_1_4/DEMUX_1_4.vcd
$date
  Thu Nov 10 17:14:20 2022
$end
$version
  GHDL v0
$end
$timescale
  1 fs
$end
$scope module standard $end
$upscope $end
$scope module std_logic_1164 $end
$upscope $end
$scope module tb_demux_1_4 $end
$var reg 1 ! x0 $end
$var reg 1 " y0 $end
$var reg 1 # y1 $end
$var reg 1 $ y2 $end
$var reg 1 % y3 $end
$var reg 2 & s[1:0] $end
$scope module simblk00 $end
$var reg 1 ' x0 $end
$var reg 2 ( s[1:0] $end
$var reg 1 ) y0 $end
$var reg 1 * y1 $end
$var reg 1 + y2 $end
$var reg 1 , y3 $end
$upscope $end
$upscope $end
$enddefinitions $end
#0
0!
0"
0#
0$
0%
b00 &
0'
b00 (
0)
0*
0+
0,
#20000000
1!
1"
1'
1)
#40000000
0"
1#
b01 &
b01 (
0)
1*
#60000000
0!
0#
0'
0*
#80000000
b10 &
b10 (
#100000000
1!
1$
1'
1+
#120000000
0$
1%
b11 &
b11 (
0+
1,
#140000000
0!
0%
0'
0,
