Maquinas de estados Finitos/Control de agua/Control_llenado.vhd
-- Control de llenado de tanque de liquido en vhd

LIBRARY IEEE;
USE IEEE.std_logic_1164.all;

Entity Control_llenado is
    port(
        RST  : in  std_logic;    -- Reset Maestro
        CLK  : in  std_logic;    -- Relog Maestro
        B    : in  std_logic;    -- Limite inferior
        T    : in  std_logic;    -- Limite superior
        M    : out  std_logic    -- Encendido de la bomba
    );
end Control_llenado;

Architecture FSM of Control_llenado is
signal Qn, Qp : std_logic;       -- Estados de mi maquina
begin
    Combinacional: process(Qp,B,T)
    begin
        if (Qp = '0') then
            --Estado apagado de la bomba
        M <= '0';
            if(B = '0' AND T = '0') then
                -- Ir a estado de encendido
                Qn <= '1';
            else
                -- permanecer apagado
                Qn <= Qp;
            end if;
        else
            -- estado de encendido
            M <= '1';
            if(B = '1' AND T = '1') then
                -- ir al estado de apagado
                Qn <= '0';
            else
                --permanecer encendido
                Qn <= Qp;
            end if;
        end if;
    end Process Combinacional;
    
    Secuencial: process(RST,CLK)
    begin
        if(RST = '0') then
            Qp <= '0';
        elsif(CLK'EVENT AND CLK='1') then
            Qp <= Qn;
        end if;
    end process Secuencial;
end FSM;

Maquinas de estados Finitos/Control de agua/TB_Control_llenado.vhd
LIBRARY IEEE;
USE IEEE.std_logic_1164.all;

entity TB_Control_llenado is
end TB_Control_llenado;

Architecture banco of TB_Control_llenado is
    component Control_llenado
        port(
            RST  : in  std_logic;    -- Reset Maestro
            CLK  : in  std_logic;    -- Relog Maestro
            B    : in  std_logic;    -- Limite inferior
            T    : in  std_logic;    -- Limite superior
            M    : out  std_logic    -- Encendido de la bomba
        );
    end component;
    signal RST, CLK, B, T, M : std_logic;
    begin
        -- Instancia del dispositivo a probar
        SIMBLK00: Control_llenado PORT MAP (RST, CLK, B, T, M);

        -- GENERAR BASE DE TIEMPO PARA CLK
        BASE: PROCESS
        BEGIN 
            CLK <= '0';
            WAIT FOR 50 ns;
            CLK <= '1';
            WAIT FOR 50 ns;
        end process BASE;
        -- inicialización por reset
        RESET: process
        begin
            RST <= '0';
            wait for 110 ns;
            RST <= '1';
            WAIT;
        END PROCESS RESET;

        -- ENTRADAS A Y B 

        ENTRADAS: PROCESS
        begin
            B<='1'; -- INICIALMENTE EL TANQUE ESTA LLENO
            T<='1';
            wait for 425 ns;
            B<='1'; -- El Tanque comienza a vaciarce
            T<='0';
            wait for 300 ns;
            B<='0'; -- El tanque esta vacio
            T<='0';
            wait for 300 ns;
            B<='1'; -- El tanque emieza a llenarse
            T<='0';
            wait for 300 ns;
            B<='1'; -- El tanque esta lleno
            T<='1';
            wait;
        end process ENTRADAS;
END banco;

Maquinas de estados Finitos/Control de agua/llenado.vcd
$date
  Mon Aug  1 17:17:11 2022
$end
$version
  GHDL v0
$end
$timescale
  1 fs
$end
$scope module standard $end
$upscope $end
$scope module std_logic_1164 $end
$upscope $end
$scope module tb_control_llenado $end
$var reg 1 ! rst $end
$var reg 1 " clk $end
$var reg 1 # b $end
$var reg 1 $ t $end
$var reg 1 % m $end
$scope module simblk00 $end
$var reg 1 & rst $end
$var reg 1 ' clk $end
$var reg 1 ( b $end
$var reg 1 ) t $end
$var reg 1 * m $end
$var reg 1 + qn $end
$var reg 1 , qp $end
$upscope $end
$upscope $end
$enddefinitions $end
#0
0!
0"
1#
1$
0%
0&
0'
1(
1)
0*
0+
0,
#50000000
1"
1'
#100000000
0"
0'
#110000000
1!
1&
#150000000
1"
1'
#200000000
0"
0'
#250000000
1"
1'
#300000000
0"
0'
#350000000
1"
1'
#400000000
0"
0'
#425000000
0$
0)
#450000000
1"
1'
#500000000
0"
0'
#550000000
1"
1'
#600000000
0"
0'
#650000000
1"
1'
#700000000
0"
0'
#725000000
0#
0(
1+
#750000000
1"
1%
1'
1*
1,
#800000000
0"
0'
#850000000
1"
1'
#900000000
0"
0'
#950000000
1"
1'
#1000000000
0"
0'
#1025000000
1#
1(
#1050000000
1"
1'
#1100000000
0"
0'
#1150000000
1"
1'
#1200000000
0"
0'
#1250000000
1"
1'
#1300000000
0"
0'
#1325000000
1$
1)
0+
#1350000000
1"
0%
1'
0*
0,
