Codificador_BCD_7SEG/Codificador_BCD_7SEG.vhd
LIBRARY IEEE;
use IEEE.std_logic_1164.all;

Entity Codificador_BCD_7SEG is
    port(
        X : in std_logic_vector(3 downto 0);
        Y : out std_logic_vector(6 downto 0)); -- abcdefg
End Codificador_BCD_7SEG;

Architecture Behavioral of Codificador_BCD_7SEG is
    Begin
        process(X)
        begin
            case X is
                when "0000" =>  Y <= "1111110"; -- 0 
                when "0001" =>  Y <= "0110000"; -- 1
                when "0010" =>  Y <= "1101101"; -- 2
                when "0011" =>  Y <= "1111001"; -- 3
                when "0100" =>  Y <= "0110011"; -- 4
                when "0101" =>  Y <= "1011011"; -- 5
                when "0110" =>  Y <= "1011111"; -- 6
                when "0111" =>  Y <= "1110001"; -- 7
                when "1000" =>  Y <= "1111111"; -- 8
                when "1001" =>  Y <= "1110011"; -- 9
                when others =>  Y <= "0000000"; -- --
            end case;
        end process;
End Behavioral;

Codificador_BCD_7SEG/TB_Codificador_BCD_7SEG.vhd

LIBRARY IEEE;
use IEEE.std_logic_1164.all;

Entity TB_Codificador_BCD_7SEG is
End TB_Codificador_BCD_7SEG;

Architecture simulation of TB_Codificador_BCD_7SEG is
    component Codificador_BCD_7SEG is
    port(
        X : in std_logic_vector(3 downto 0);
        Y : out std_logic_vector(6 downto 0)); -- abcdefg
    end component;
    signal X : std_logic_vector(3 downto 0);
    signal Y : std_logic_vector(6 downto 0);
    
    begin
        SIMBLK01 : Codificador_BCD_7SEG PORT MAP (X,Y);
        
        process
        begin
            --
            X <= "0000";
            wait for 20 ns;
            --
            X <= "0001";
            wait for 20 ns;
            --
            X <= "0010";
            wait for 20 ns;
            --
            X <= "0011";
            wait for 20 ns;
            --
            X <= "0100";
            wait for 20 ns;
            --
            X <= "0101";
            wait for 20 ns;
            --
            X <= "0110";
            wait for 20 ns;
            --
            X <= "0111";
            wait for 20 ns;
            --
            X <= "1000";
            wait for 20 ns;
            --
            X <= "1001";
            wait for 20 ns;
            --
            X <= "1010";
            wait for 20 ns;
            --
            X <= "1011";
            wait for 20 ns;
            --
            X <= "1100";
            wait for 20 ns;
            --
            X <= "1101";
            wait for 20 ns;
            --
            X <= "1110";
            wait for 20 ns;
            --
            X <= "1111";
            wait;
        end process;
End simulation;

Codificador_BCD_7SEG/BCD7SEG.vcd
$date
  Mon Nov 14 16:52:17 2022
$end
$version
  GHDL v0
$end
$timescale
  1 fs
$end
$scope module standard $end
$upscope $end
$scope module std_logic_1164 $end
$upscope $end
$scope module tb_codificador_bcd_7seg $end
$var reg 4 ! x[3:0] $end
$var reg 7 " y[6:0] $end
$scope module simblk01 $end
$var reg 4 # x[3:0] $end
$var reg 7 $ y[6:0] $end
$upscope $end
$upscope $end
$enddefinitions $end
#0
b0000 !
b1111110 "
b0000 #
b1111110 $
#20000000
b0001 !
b0110000 "
b0001 #
b0110000 $
#40000000
b0010 !
b1101101 "
b0010 #
b1101101 $
#60000000
b0011 !
b1111001 "
b0011 #
b1111001 $
#80000000
b0100 !
b0110011 "
b0100 #
b0110011 $
#100000000
b0101 !
b1011011 "
b0101 #
b1011011 $
#120000000
b0110 !
b1011111 "
b0110 #
b1011111 $
#140000000
b0111 !
b1110001 "
b0111 #
b1110001 $
#160000000
b1000 !
b1111111 "
b1000 #
b1111111 $
#180000000
b1001 !
b1110011 "
b1001 #
b1110011 $
#200000000
b1010 !
b0000000 "
b1010 #
b0000000 $
#220000000
b1011 !
b1011 #
#240000000
b1100 !
b1100 #
#260000000
b1101 !
b1101 #
#280000000
b1110 !
b1110 #
#300000000
b1111 !
b1111 #
